iranian_validators/__init__.py
iranian_validators/validators.py
iranian_validators-0.1.0.dist-info/METADATA
iranian_validators-0.1.0.dist-info/WHEEL
iranian_validators-0.1.0.dist-info/top_level.txt
iranian_validators-0.1.0.dist-info/RECORD
