Metadata-Version: 2.1
Name: iranian-validators
Version: 0.1.0
Summary: A package for validating Iranian national code, mobile number, and more.
Home-page: https://mrvafaei.com
Author: MrVafaei
Author-email: mvmsoft7@gmail.com
License: UNKNOWN
Platform: UNKNOWN
Classifier: Programming Language :: Python :: 3
Classifier: License :: OSI Approved :: MIT License
Classifier: Operating System :: OS Independent
Requires-Python: >=3.6
